rssht_controller_qt/__init__.py
rssht_controller_qt/config.py
rssht_controller_qt/data_access.py
rssht_controller_qt/main.py
rssht_controller_qt/resources.py
rssht_controller_qt/util.py
rssht_controller_qt/views.py
remote_ssh_tunnel_controller_qt-0.6.0.dist-info/LICENSE
remote_ssh_tunnel_controller_qt-0.6.0.dist-info/METADATA
remote_ssh_tunnel_controller_qt-0.6.0.dist-info/WHEEL
remote_ssh_tunnel_controller_qt-0.6.0.dist-info/entry_points.txt
remote_ssh_tunnel_controller_qt-0.6.0.dist-info/top_level.txt
remote_ssh_tunnel_controller_qt-0.6.0.dist-info/RECORD
