Metadata-Version: 2.1
Name: remote-ssh-tunnel-controller-qt
Version: 0.6.0
Summary: Remote SSH Tunnel (RSSHT) controller - Qt frontend
Home-page: https://github.com/guallo/remote-ssh-tunnel-controller-qt
Author: The remote-ssh-tunnel-controller-qt Authors
Author-email: guallo.username@gmail.com
License: UNKNOWN
Platform: UNKNOWN
Classifier: Programming Language :: Python :: 3
Classifier: License :: OSI Approved :: MIT License
Classifier: Operating System :: OS Independent
Requires-Python: >=3.6
Requires-Dist: remote-ssh-tunnel-controller-lib (<1,>=0.1.0)
Requires-Dist: PySide2 (<5.15,>=5.14.2.2)
